src/topsis.py
Topsis_hasika_102003542-0.1.0.dist-info/METADATA
Topsis_hasika_102003542-0.1.0.dist-info/WHEEL
Topsis_hasika_102003542-0.1.0.dist-info/entry_points.txt
Topsis_hasika_102003542-0.1.0.dist-info/top_level.txt
Topsis_hasika_102003542-0.1.0.dist-info/RECORD
