Metadata-Version: 2.1
Name: Topsis-hasika-102003542
Version: 0.1.0
Summary: A Python package for implementing TOPSIS technique.
Home-page: UNKNOWN
Author: Hasika Tandon
Author-email: htandon_be20@thapar.edu
License: MIT
Platform: UNKNOWN
Classifier: License :: OSI Approved :: MIT License
Classifier: Programming Language :: Python :: 3
Classifier: Programming Language :: Python :: 3.4
Classifier: Programming Language :: Python :: 3.5
Classifier: Programming Language :: Python :: 3.6
Classifier: Programming Language :: Python :: 3.7
Requires-Dist: scipy
Requires-Dist: tabulate
Requires-Dist: numpy
Requires-Dist: pandas
